MANIFEST.in
README.md
setup.py
pub_worm/__init__.py
pub_worm.egg-info/PKG-INFO
pub_worm.egg-info/SOURCES.txt
pub_worm.egg-info/dependency_links.txt
pub_worm.egg-info/not-zip-safe
pub_worm.egg-info/requires.txt
pub_worm.egg-info/top_level.txt
pub_worm/biorxiv/__init__.py
pub_worm/biorxiv/biorxiv_api.py
pub_worm/ensembl/__init__.py
pub_worm/ensembl/ensembl_api.py
pub_worm/impact_factor/__init__.py
pub_worm/impact_factor/impact_factor_lookup.py
pub_worm/impact_factor/data/2022_JCR_IF.csv
pub_worm/ncbi/__init__.py
pub_worm/ncbi/entreze_api.py
pub_worm/orcid/__init__.py
pub_worm/orcid/orcid_api.py
pub_worm/wormbase/__init__.py
pub_worm/wormbase/to_csv_helpers.py
pub_worm/wormbase/wormbase_api.py
pub_worm/wormbase/wormbase_util.py
pub_worm/wormbase/data/wormbase_field_gene.json
pub_worm/wormbase/data/wormbase_field_paper.json
pub_worm/wormbase/data/wormbase_widget_gene.json
tests/__init__.py
tests/impact_factor/__init__.py
tests/impact_factor/test_get_impact_factor.py
tests/ncbi/__init__.py
tests/ncbi/test_entreze_api.py
tests/orcid/__init__.py
tests/orcid/test_orcid_api.py
tests/wormbase/__init__.py
tests/wormbase/test_wormbase_api.py