Metadata-Version: 2.1
Name: pub-worm
Version: 0.3.10
Summary: Wormbase/PudMed API Access
Home-page: https://github.com/DanHUMassMed/pub_worm.git
Author: Dan Higgins
Author-email: daniel.higgins@yahoo.com
License: MIT
Requires-Dist: pandas==2.2.3
Requires-Dist: beautifulsoup4==4.12.3
Requires-Dist: requests==2.31.0
Requires-Dist: aiohttp==3.9.5
Requires-Dist: aiofiles==24.1.0
